{
  "hero": {
    "title": "Free skill up your programming languages",
    "content": "Ultricies mi eget mauris pharetra et ultrices neque. Scelerisque in dictum non consectetur a erat nam at lectus. Sit amet risus nullam eget felis.",
    "btn_name": "Explore Now",
    "thumb": "/images/banner/thumb1.png",
    "counter": [
      {
        "id": 1,
        "point": "98K+",
        "topic": "Artwork"
      },
      {
        "id": 2,
        "point": "12K+",
        "topic": "Auction"
      },
      {
        "id": 3,
        "point": "15K+",
        "topic": "Artist"
      }
    ],
    "banner": [
      {
        "id": 1,
        "image": "./images/banner/banner-1.png",
        "title": "Abstr Gradient NFT",
        "author": "/images/person/person-1.png",
        "author_name": "Arkhan17",
        "badge": {
          "title": "Current Bid",
          "bid_price": "0.25 ETH",
          "ends_time": "Ends in",
          "bid_hour": "12h  43m  42s"
        }
      }
    ]
  }
}